{
  "source_file": "data/filted/TPDM,113,訴,479,20250108,1.json",
  "detection_method": "hybrid_rule_bert",
  "bert_model_used": true,
  "timestamp": "2025-10-12T11:26:53.798321",
  "processing_time": 0.11253094673156738,
  "statistics": {
    "total_lines": 311,
    "candidate_lines": 43,
    "bert_processed_lines": 43,
    "total_markers": 42,
    "ultra_strict_markers": 0,
    "bert_refined_markers": 42,
    "rule_only_markers": 0
  },
  "analysis": {
    "total_lines": 311,
    "positive_predictions": 42,
    "positive_ratio": 0.13504823151125403,
    "ultra_strict_count": 0,
    "method_statistics": {
      "rule_rejected": {
        "total": 261,
        "positive": 0
      },
      "empty_line": {
        "total": 7,
        "positive": 0
      },
      "soft_rule_bert": {
        "total": 43,
        "positive": 42
      }
    },
    "symbol_category_distribution": {
      "中文數字": 31,
      "圍字數字": 11
    },
    "bert_score_stats": {
      "mean": 0.976605009753257,
      "std": 0.15021340361194252,
      "min": 0.00311090936884284,
      "max": 0.999819815158844,
      "count": 43
    }
  },
  "markers": [
    {
      "line_number": 20,
      "symbol": "一",
      "unicode_code": "U+4E00",
      "category": "中文數字",
      "content": "一、本件犯罪事實及證據，除補充「被告於本院準備程序及審理",
      "rule_score": 0.5,
      "bert_score": 0.9998086094856262,
      "method": "soft_rule_bert",
      "is_pua": false
    },
    {
      "line_number": 22,
      "symbol": "二",
      "unicode_code": "U+4E8C",
      "category": "中文數字",
      "content": "二、新舊法比較：",
      "rule_score": 0.5,
      "bert_score": 0.9997937083244324,
      "method": "soft_rule_bert",
      "is_pua": false
    },
    {
      "line_number": 26,
      "symbol": "㈠",
      "unicode_code": "U+3220",
      "category": "圍字數字",
      "content": "㈠查被告郭之凡於行為後，組織犯罪防制條例第3條、第4條、",
      "rule_score": 0.5,
      "bert_score": 0.9997511506080627,
      "method": "soft_rule_bert",
      "is_pua": false
    },
    {
      "line_number": 52,
      "symbol": "㈡",
      "unicode_code": "U+3221",
      "category": "圍字數字",
      "content": "㈡查被告行為後，刑法第339條之4規定業於112年5月31日修正",
      "rule_score": 0.5,
      "bert_score": 0.9997534155845642,
      "method": "soft_rule_bert",
      "is_pua": false
    },
    {
      "line_number": 59,
      "symbol": "㈢",
      "unicode_code": "U+3222",
      "category": "圍字數字",
      "content": "㈢又被告行為後，洗錢防制法第16條第2項業於112年6月14日修",
      "rule_score": 0.5,
      "bert_score": 0.9997374415397644,
      "method": "soft_rule_bert",
      "is_pua": false
    },
    {
      "line_number": 70,
      "symbol": "㈣",
      "unicode_code": "U+3223",
      "category": "圍字數字",
      "content": "㈣又詐欺犯罪危害防制條例亦於被告行為後之113年7月31日增",
      "rule_score": 0.5,
      "bert_score": 0.9997383952140808,
      "method": "soft_rule_bert",
      "is_pua": false
    },
    {
      "line_number": 81,
      "symbol": "三",
      "unicode_code": "U+4E09",
      "category": "中文數字",
      "content": "三、論罪科刑：",
      "rule_score": 0.5,
      "bert_score": 0.9997953772544861,
      "method": "soft_rule_bert",
      "is_pua": false
    },
    {
      "line_number": 82,
      "symbol": "㈠",
      "unicode_code": "U+3220",
      "category": "圍字數字",
      "content": "㈠查被告郭之凡因參與洪鼎清、林鑫宏及年籍不詳成員「言言",
      "rule_score": 0.5,
      "bert_score": 0.9997453093528748,
      "method": "soft_rule_bert",
      "is_pua": false
    },
    {
      "line_number": 90,
      "symbol": "㈡",
      "unicode_code": "U+3221",
      "category": "圍字數字",
      "content": "㈡被告參與上開詐欺集團，擔任交付薪水予集團成員或帳戶提",
      "rule_score": 0.5,
      "bert_score": 0.999700665473938,
      "method": "soft_rule_bert",
      "is_pua": false
    },
    {
      "line_number": 95,
      "symbol": "㈢",
      "unicode_code": "U+3222",
      "category": "圍字數字",
      "content": "㈢是核被告就附表編號9所示之被害人，為本案最先繫屬於法院",
      "rule_score": 0.5,
      "bert_score": 0.9997556805610657,
      "method": "soft_rule_bert",
      "is_pua": false
    },
    {
      "line_number": 99,
      "symbol": "㈣",
      "unicode_code": "U+3223",
      "category": "圍字數字",
      "content": "㈣被告與洪鼎清、林鑫宏及年籍不詳成員「言言」、「李九齡",
      "rule_score": 0.5,
      "bert_score": 0.9997320771217346,
      "method": "soft_rule_bert",
      "is_pua": false
    },
    {
      "line_number": 102,
      "symbol": "㈤",
      "unicode_code": "U+3224",
      "category": "圍字數字",
      "content": "㈤被告就附表編號9所示首次參與犯罪組織，而與其所屬詐欺集",
      "rule_score": 0.5,
      "bert_score": 0.9997190833091736,
      "method": "soft_rule_bert",
      "is_pua": false
    },
    {
      "line_number": 112,
      "symbol": "㈥",
      "unicode_code": "U+3225",
      "category": "圍字數字",
      "content": "㈥被告於本院審理時均坦認本案洗錢犯行，核與修正前洗錢防",
      "rule_score": 0.5,
      "bert_score": 0.9997283816337585,
      "method": "soft_rule_bert",
      "is_pua": false
    },
    {
      "line_number": 117,
      "symbol": "㈦",
      "unicode_code": "U+3226",
      "category": "圍字數字",
      "content": "㈦爰以行為人責任為基礎，審酌我國近年治安飽受詐騙集團威",
      "rule_score": 0.5,
      "bert_score": 0.9997784495353699,
      "method": "soft_rule_bert",
      "is_pua": false
    },
    {
      "line_number": 137,
      "symbol": "四",
      "unicode_code": "U+56DB",
      "category": "中文數字",
      "content": "四、被告於警詢中即供稱：我加入詐欺集團每月大約獲得8至10",
      "rule_score": 0.5,
      "bert_score": 0.9998061060905457,
      "method": "soft_rule_bert",
      "is_pua": false
    },
    {
      "line_number": 148,
      "symbol": "五",
      "unicode_code": "U+4E94",
      "category": "中文數字",
      "content": "五、據上論斷，應依刑事訴訟法第273條之1第1項、第299條第1",
      "rule_score": 0.5,
      "bert_score": 0.9997907280921936,
      "method": "soft_rule_bert",
      "is_pua": false
    },
    {
      "line_number": 150,
      "symbol": "六",
      "unicode_code": "U+516D",
      "category": "中文數字",
      "content": "六、如不服本判決應於收受送達後20日內向本院提出上訴書狀，",
      "rule_score": 0.5,
      "bert_score": 0.9997807145118713,
      "method": "soft_rule_bert",
      "is_pua": false
    },
    {
      "line_number": 166,
      "symbol": "一",
      "unicode_code": "U+4E00",
      "category": "中文數字",
      "content": "一、冒用政府機關或公務員名義犯之。",
      "rule_score": 0.5,
      "bert_score": 0.999803364276886,
      "method": "soft_rule_bert",
      "is_pua": false
    },
    {
      "line_number": 167,
      "symbol": "二",
      "unicode_code": "U+4E8C",
      "category": "中文數字",
      "content": "二、三人以上共同犯之。",
      "rule_score": 0.5,
      "bert_score": 0.999819815158844,
      "method": "soft_rule_bert",
      "is_pua": false
    },
    {
      "line_number": 168,
      "symbol": "三",
      "unicode_code": "U+4E09",
      "category": "中文數字",
      "content": "三、以廣播電視、電子通訊、網際網路或其他媒體等傳播工具，",
      "rule_score": 0.5,
      "bert_score": 0.9997977614402771,
      "method": "soft_rule_bert",
      "is_pua": false
    },
    {
      "line_number": 179,
      "symbol": "一",
      "unicode_code": "U+4E00",
      "category": "中文數字",
      "content": "一、出售財產、商業組織之出資或股份或放棄經營權。",
      "rule_score": 0.5,
      "bert_score": 0.999804675579071,
      "method": "soft_rule_bert",
      "is_pua": false
    },
    {
      "line_number": 180,
      "symbol": "二",
      "unicode_code": "U+4E8C",
      "category": "中文數字",
      "content": "二、配合辦理都市更新重建之處理程序。",
      "rule_score": 0.5,
      "bert_score": 0.9997885823249817,
      "method": "soft_rule_bert",
      "is_pua": false
    },
    {
      "line_number": 181,
      "symbol": "三",
      "unicode_code": "U+4E09",
      "category": "中文數字",
      "content": "三、購買商品或支付勞務報酬。",
      "rule_score": 0.5,
      "bert_score": 0.9997863173484802,
      "method": "soft_rule_bert",
      "is_pua": false
    },
    {
      "line_number": 182,
      "symbol": "四",
      "unicode_code": "U+56DB",
      "category": "中文數字",
      "content": "四、履行債務或接受債務協商之內容。",
      "rule_score": 0.5,
      "bert_score": 0.9997861981391907,
      "method": "soft_rule_bert",
      "is_pua": false
    },
    {
      "line_number": 185,
      "symbol": "一",
      "unicode_code": "U+4E00",
      "category": "中文數字",
      "content": "一、使人行無義務之事或妨害其行使權利。",
      "rule_score": 0.5,
      "bert_score": 0.9998109936714172,
      "method": "soft_rule_bert",
      "is_pua": false
    },
    {
      "line_number": 186,
      "symbol": "二",
      "unicode_code": "U+4E8C",
      "category": "中文數字",
      "content": "二、在公共場所或公眾得出入之場所聚集三人以上，已受該管公",
      "rule_score": 0.5,
      "bert_score": 0.9998016953468323,
      "method": "soft_rule_bert",
      "is_pua": false
    },
    {
      "line_number": 207,
      "symbol": "一",
      "unicode_code": "U+4E00",
      "category": "中文數字",
      "content": "一、郭之凡（原名：郭鈞維，綽號阿川，TELEGRAM通訊軟體暱稱",
      "rule_score": 0.5,
      "bert_score": 0.9997907280921936,
      "method": "soft_rule_bert",
      "is_pua": false
    },
    {
      "line_number": 236,
      "symbol": "二",
      "unicode_code": "U+4E8C",
      "category": "中文數字",
      "content": "二、案經陳秀琪、陳素姿、葉叡緹、王金香、張文鐘、游雅琦、",
      "rule_score": 0.5,
      "bert_score": 0.9998005032539368,
      "method": "soft_rule_bert",
      "is_pua": false
    },
    {
      "line_number": 241,
      "symbol": "一",
      "unicode_code": "U+4E00",
      "category": "中文數字",
      "content": "一、證據清單及待證事實：",
      "rule_score": 0.5,
      "bert_score": 0.9998032450675964,
      "method": "soft_rule_bert",
      "is_pua": false
    },
    {
      "line_number": 243,
      "symbol": "二",
      "unicode_code": "U+4E8C",
      "category": "中文數字",
      "content": "二、核被告對附表編號9所示之被害人所為，為其參與本案詐騙",
      "rule_score": 0.5,
      "bert_score": 0.9998120665550232,
      "method": "soft_rule_bert",
      "is_pua": false
    },
    {
      "line_number": 256,
      "symbol": "三",
      "unicode_code": "U+4E09",
      "category": "中文數字",
      "content": "三、按數人共犯一罪或數罪者，為相牽連案件，刑事訴訟法第7",
      "rule_score": 0.5,
      "bert_score": 0.9998039603233337,
      "method": "soft_rule_bert",
      "is_pua": false
    },
    {
      "line_number": 265,
      "symbol": "四",
      "unicode_code": "U+56DB",
      "category": "中文數字",
      "content": "四、依刑事訴訟法第265條第1項追加起訴。",
      "rule_score": 0.5,
      "bert_score": 0.9997854828834534,
      "method": "soft_rule_bert",
      "is_pua": false
    },
    {
      "line_number": 277,
      "symbol": "一",
      "unicode_code": "U+4E00",
      "category": "中文數字",
      "content": "一、冒用政府機關或公務員名義犯之。",
      "rule_score": 0.5,
      "bert_score": 0.999803364276886,
      "method": "soft_rule_bert",
      "is_pua": false
    },
    {
      "line_number": 278,
      "symbol": "二",
      "unicode_code": "U+4E8C",
      "category": "中文數字",
      "content": "二、三人以上共同犯之。",
      "rule_score": 0.5,
      "bert_score": 0.999819815158844,
      "method": "soft_rule_bert",
      "is_pua": false
    },
    {
      "line_number": 279,
      "symbol": "三",
      "unicode_code": "U+4E09",
      "category": "中文數字",
      "content": "三、以廣播電視、電子通訊、網際網路或其他媒體等傳播工具，",
      "rule_score": 0.5,
      "bert_score": 0.9997977614402771,
      "method": "soft_rule_bert",
      "is_pua": false
    },
    {
      "line_number": 281,
      "symbol": "四",
      "unicode_code": "U+56DB",
      "category": "中文數字",
      "content": "四、以電腦合成或其他科技方法製作關於他人不實影像、聲音或",
      "rule_score": 0.5,
      "bert_score": 0.9997944235801697,
      "method": "soft_rule_bert",
      "is_pua": false
    },
    {
      "line_number": 299,
      "symbol": "一",
      "unicode_code": "U+4E00",
      "category": "中文數字",
      "content": "一、出售財產、商業組織之出資或股份或放棄經營權。",
      "rule_score": 0.5,
      "bert_score": 0.999804675579071,
      "method": "soft_rule_bert",
      "is_pua": false
    },
    {
      "line_number": 300,
      "symbol": "二",
      "unicode_code": "U+4E8C",
      "category": "中文數字",
      "content": "二、配合辦理都市更新重建之處理程序。",
      "rule_score": 0.5,
      "bert_score": 0.9997885823249817,
      "method": "soft_rule_bert",
      "is_pua": false
    },
    {
      "line_number": 301,
      "symbol": "三",
      "unicode_code": "U+4E09",
      "category": "中文數字",
      "content": "三、購買商品或支付勞務報酬。",
      "rule_score": 0.5,
      "bert_score": 0.9997863173484802,
      "method": "soft_rule_bert",
      "is_pua": false
    },
    {
      "line_number": 302,
      "symbol": "四",
      "unicode_code": "U+56DB",
      "category": "中文數字",
      "content": "四、履行債務或接受債務協商之內容。",
      "rule_score": 0.5,
      "bert_score": 0.9997861981391907,
      "method": "soft_rule_bert",
      "is_pua": false
    },
    {
      "line_number": 305,
      "symbol": "一",
      "unicode_code": "U+4E00",
      "category": "中文數字",
      "content": "一、使人行無義務之事或妨害其行使權利。",
      "rule_score": 0.5,
      "bert_score": 0.9998109936714172,
      "method": "soft_rule_bert",
      "is_pua": false
    },
    {
      "line_number": 306,
      "symbol": "二",
      "unicode_code": "U+4E8C",
      "category": "中文數字",
      "content": "二、在公共場所或公眾得出入之場所聚集三人以上，已受該管公",
      "rule_score": 0.5,
      "bert_score": 0.9998016953468323,
      "method": "soft_rule_bert",
      "is_pua": false
    }
  ]
}