{
  "source_file": "data/filted/TPDM,113,審訴,2676,20250122,1.json",
  "detection_method": "hybrid_rule_bert",
  "bert_model_used": true,
  "timestamp": "2025-10-12T11:26:18.674005",
  "processing_time": 0.11167430877685547,
  "statistics": {
    "total_lines": 339,
    "candidate_lines": 42,
    "bert_processed_lines": 42,
    "total_markers": 36,
    "ultra_strict_markers": 0,
    "bert_refined_markers": 36,
    "rule_only_markers": 0
  },
  "analysis": {
    "total_lines": 339,
    "positive_predictions": 36,
    "positive_ratio": 0.10619469026548672,
    "ultra_strict_count": 0,
    "method_statistics": {
      "rule_rejected": {
        "total": 285,
        "positive": 0
      },
      "empty_line": {
        "total": 12,
        "positive": 0
      },
      "soft_rule_bert": {
        "total": 42,
        "positive": 36
      }
    },
    "symbol_category_distribution": {
      "中文數字": 26,
      "圍字數字": 10
    },
    "bert_score_stats": {
      "mean": 0.8574731490752172,
      "std": 0.34859405062269194,
      "min": 0.0031906855292618275,
      "max": 0.999819815158844,
      "count": 42
    }
  },
  "markers": [
    {
      "line_number": 25,
      "symbol": "一",
      "unicode_code": "U+4E00",
      "category": "中文數字",
      "content": "一、本件犯罪事實及證據，除犯罪事實欄一倒數第7行「薛揚昱",
      "rule_score": 0.5,
      "bert_score": 0.9998040795326233,
      "method": "soft_rule_bert",
      "is_pua": false
    },
    {
      "line_number": 32,
      "symbol": "二",
      "unicode_code": "U+4E8C",
      "category": "中文數字",
      "content": "二、論罪科刑：",
      "rule_score": 0.5,
      "bert_score": 0.9997956156730652,
      "method": "soft_rule_bert",
      "is_pua": false
    },
    {
      "line_number": 33,
      "symbol": "㈠",
      "unicode_code": "U+3220",
      "category": "圍字數字",
      "content": "㈠新舊法比較：按行為後法律有變更者，適用行為時之法律，",
      "rule_score": 0.5,
      "bert_score": 0.9997650980949402,
      "method": "soft_rule_bert",
      "is_pua": false
    },
    {
      "line_number": 84,
      "symbol": "㈡",
      "unicode_code": "U+3221",
      "category": "圍字數字",
      "content": "㈡核被告2人所為，均係犯刑法第339條之4第1項第2款之三人以",
      "rule_score": 0.5,
      "bert_score": 0.9997405409812927,
      "method": "soft_rule_bert",
      "is_pua": false
    },
    {
      "line_number": 88,
      "symbol": "㈢",
      "unicode_code": "U+3222",
      "category": "圍字數字",
      "content": "㈢被告楊憲承共同偽造「同信儲值證券部」印文1枚及「陳友駿",
      "rule_score": 0.5,
      "bert_score": 0.9997432827949524,
      "method": "soft_rule_bert",
      "is_pua": false
    },
    {
      "line_number": 95,
      "symbol": "㈣",
      "unicode_code": "U+3223",
      "category": "圍字數字",
      "content": "㈣被告2人與其所組成之詐欺集團不詳成員就本件犯行，有犯意",
      "rule_score": 0.5,
      "bert_score": 0.9997243285179138,
      "method": "soft_rule_bert",
      "is_pua": false
    },
    {
      "line_number": 97,
      "symbol": "㈤",
      "unicode_code": "U+3224",
      "category": "圍字數字",
      "content": "㈤被告2人前開所犯之數罪名，均係在同一犯罪決意及預定計畫",
      "rule_score": 0.5,
      "bert_score": 0.9997109770774841,
      "method": "soft_rule_bert",
      "is_pua": false
    },
    {
      "line_number": 102,
      "symbol": "㈥",
      "unicode_code": "U+3225",
      "category": "圍字數字",
      "content": "㈥被告楊憲承前因違反洗錢防制法等案件，經臺灣橋頭地方法",
      "rule_score": 0.5,
      "bert_score": 0.9997522234916687,
      "method": "soft_rule_bert",
      "is_pua": false
    },
    {
      "line_number": 112,
      "symbol": "㈦",
      "unicode_code": "U+3226",
      "category": "圍字數字",
      "content": "㈦被告2人行為後，詐欺犯罪危害防制條例於113年7月31日公布",
      "rule_score": 0.5,
      "bert_score": 0.999777615070343,
      "method": "soft_rule_bert",
      "is_pua": false
    },
    {
      "line_number": 121,
      "symbol": "㈧",
      "unicode_code": "U+3227",
      "category": "圍字數字",
      "content": "㈧爰審酌被告楊憲承加入詐欺集團擔任負責偽造收據之分工角",
      "rule_score": 0.5,
      "bert_score": 0.999774158000946,
      "method": "soft_rule_bert",
      "is_pua": false
    },
    {
      "line_number": 130,
      "symbol": "三",
      "unicode_code": "U+4E09",
      "category": "中文數字",
      "content": "三、沒收：",
      "rule_score": 0.5,
      "bert_score": 0.9998018145561218,
      "method": "soft_rule_bert",
      "is_pua": false
    },
    {
      "line_number": 141,
      "symbol": "㈠",
      "unicode_code": "U+3220",
      "category": "圍字數字",
      "content": "㈠犯罪所得、洗錢之財物部分：",
      "rule_score": 0.5,
      "bert_score": 0.9997666478157043,
      "method": "soft_rule_bert",
      "is_pua": false
    },
    {
      "line_number": 149,
      "symbol": "㈡",
      "unicode_code": "U+3221",
      "category": "圍字數字",
      "content": "㈡犯罪所用之物部分：",
      "rule_score": 0.5,
      "bert_score": 0.9997614026069641,
      "method": "soft_rule_bert",
      "is_pua": false
    },
    {
      "line_number": 156,
      "symbol": "四",
      "unicode_code": "U+56DB",
      "category": "中文數字",
      "content": "四、同案被告巫祥榮由本院另行審結，附此敘明。",
      "rule_score": 0.5,
      "bert_score": 0.9997852444648743,
      "method": "soft_rule_bert",
      "is_pua": false
    },
    {
      "line_number": 181,
      "symbol": "一",
      "unicode_code": "U+4E00",
      "category": "中文數字",
      "content": "一、冒用政府機關或公務員名義犯之。",
      "rule_score": 0.5,
      "bert_score": 0.999803364276886,
      "method": "soft_rule_bert",
      "is_pua": false
    },
    {
      "line_number": 182,
      "symbol": "二",
      "unicode_code": "U+4E8C",
      "category": "中文數字",
      "content": "二、三人以上共同犯之。",
      "rule_score": 0.5,
      "bert_score": 0.999819815158844,
      "method": "soft_rule_bert",
      "is_pua": false
    },
    {
      "line_number": 183,
      "symbol": "三",
      "unicode_code": "U+4E09",
      "category": "中文數字",
      "content": "三、以廣播電視、電子通訊、網際網路或其他媒體等傳播工具，",
      "rule_score": 0.5,
      "bert_score": 0.9997977614402771,
      "method": "soft_rule_bert",
      "is_pua": false
    },
    {
      "line_number": 185,
      "symbol": "四",
      "unicode_code": "U+56DB",
      "category": "中文數字",
      "content": "四、以電腦合成或其他科技方法製作關於他人不實影像、聲音或",
      "rule_score": 0.5,
      "bert_score": 0.9997944235801697,
      "method": "soft_rule_bert",
      "is_pua": false
    },
    {
      "line_number": 190,
      "symbol": "一",
      "unicode_code": "U+4E00",
      "category": "中文數字",
      "content": "一、隱匿特定犯罪所得或掩飾其來源。",
      "rule_score": 0.5,
      "bert_score": 0.9998007416725159,
      "method": "soft_rule_bert",
      "is_pua": false
    },
    {
      "line_number": 191,
      "symbol": "二",
      "unicode_code": "U+4E8C",
      "category": "中文數字",
      "content": "二、妨礙或危害國家對於特定犯罪所得之調查、發現、保全、沒",
      "rule_score": 0.5,
      "bert_score": 0.9998070597648621,
      "method": "soft_rule_bert",
      "is_pua": false
    },
    {
      "line_number": 193,
      "symbol": "三",
      "unicode_code": "U+4E09",
      "category": "中文數字",
      "content": "三、收受、持有或使用他人之特定犯罪所得。",
      "rule_score": 0.5,
      "bert_score": 0.9997921586036682,
      "method": "soft_rule_bert",
      "is_pua": false
    },
    {
      "line_number": 194,
      "symbol": "四",
      "unicode_code": "U+56DB",
      "category": "中文數字",
      "content": "四、使用自己之特定犯罪所得與他人進行交易。",
      "rule_score": 0.5,
      "bert_score": 0.9997723698616028,
      "method": "soft_rule_bert",
      "is_pua": false
    },
    {
      "line_number": 223,
      "symbol": "一",
      "unicode_code": "U+4E00",
      "category": "中文數字",
      "content": "一、楊憲承前因詐欺案件，經臺灣橋頭地方法院以110年度金簡",
      "rule_score": 0.5,
      "bert_score": 0.999816358089447,
      "method": "soft_rule_bert",
      "is_pua": false
    },
    {
      "line_number": 249,
      "symbol": "二",
      "unicode_code": "U+4E8C",
      "category": "中文數字",
      "content": "二、案經徐彌訴請臺北市政府警察局松山分局報告偵辦。",
      "rule_score": 0.5,
      "bert_score": 0.9998119473457336,
      "method": "soft_rule_bert",
      "is_pua": false
    },
    {
      "line_number": 251,
      "symbol": "一",
      "unicode_code": "U+4E00",
      "category": "中文數字",
      "content": "一、證據清單及待證事實：",
      "rule_score": 0.5,
      "bert_score": 0.9998032450675964,
      "method": "soft_rule_bert",
      "is_pua": false
    },
    {
      "line_number": 253,
      "symbol": "二",
      "unicode_code": "U+4E8C",
      "category": "中文數字",
      "content": "二、新舊法比較：113年7月31日修正公布、同年0月0日生效施行",
      "rule_score": 0.5,
      "bert_score": 0.9998125433921814,
      "method": "soft_rule_bert",
      "is_pua": false
    },
    {
      "line_number": 278,
      "symbol": "三",
      "unicode_code": "U+4E09",
      "category": "中文數字",
      "content": "三、核被告楊憲承、薛揚昱、巫祥榮所為，均係犯刑法第339條",
      "rule_score": 0.5,
      "bert_score": 0.9997960925102234,
      "method": "soft_rule_bert",
      "is_pua": false
    },
    {
      "line_number": 296,
      "symbol": "四",
      "unicode_code": "U+56DB",
      "category": "中文數字",
      "content": "四、依刑事訴訟法第251條第1項提起公訴。",
      "rule_score": 0.5,
      "bert_score": 0.9997796416282654,
      "method": "soft_rule_bert",
      "is_pua": false
    },
    {
      "line_number": 308,
      "symbol": "一",
      "unicode_code": "U+4E00",
      "category": "中文數字",
      "content": "一、冒用政府機關或公務員名義犯之。",
      "rule_score": 0.5,
      "bert_score": 0.999803364276886,
      "method": "soft_rule_bert",
      "is_pua": false
    },
    {
      "line_number": 309,
      "symbol": "二",
      "unicode_code": "U+4E8C",
      "category": "中文數字",
      "content": "二、三人以上共同犯之。",
      "rule_score": 0.5,
      "bert_score": 0.999819815158844,
      "method": "soft_rule_bert",
      "is_pua": false
    },
    {
      "line_number": 310,
      "symbol": "三",
      "unicode_code": "U+4E09",
      "category": "中文數字",
      "content": "三、以廣播電視、電子通訊、網際網路或其他媒體等傳播工具，",
      "rule_score": 0.5,
      "bert_score": 0.9997977614402771,
      "method": "soft_rule_bert",
      "is_pua": false
    },
    {
      "line_number": 312,
      "symbol": "四",
      "unicode_code": "U+56DB",
      "category": "中文數字",
      "content": "四、以電腦合成或其他科技方法製作關於他人不實影像、聲音或",
      "rule_score": 0.5,
      "bert_score": 0.9997944235801697,
      "method": "soft_rule_bert",
      "is_pua": false
    },
    {
      "line_number": 328,
      "symbol": "一",
      "unicode_code": "U+4E00",
      "category": "中文數字",
      "content": "一、隱匿特定犯罪所得或掩飾其來源。",
      "rule_score": 0.5,
      "bert_score": 0.9998007416725159,
      "method": "soft_rule_bert",
      "is_pua": false
    },
    {
      "line_number": 329,
      "symbol": "二",
      "unicode_code": "U+4E8C",
      "category": "中文數字",
      "content": "二、妨礙或危害國家對於特定犯罪所得之調查、發現、保全、沒",
      "rule_score": 0.5,
      "bert_score": 0.9998070597648621,
      "method": "soft_rule_bert",
      "is_pua": false
    },
    {
      "line_number": 331,
      "symbol": "三",
      "unicode_code": "U+4E09",
      "category": "中文數字",
      "content": "三、收受、持有或使用他人之特定犯罪所得。",
      "rule_score": 0.5,
      "bert_score": 0.9997921586036682,
      "method": "soft_rule_bert",
      "is_pua": false
    },
    {
      "line_number": 332,
      "symbol": "四",
      "unicode_code": "U+56DB",
      "category": "中文數字",
      "content": "四、使用自己之特定犯罪所得與他人進行交易。",
      "rule_score": 0.5,
      "bert_score": 0.9997723698616028,
      "method": "soft_rule_bert",
      "is_pua": false
    }
  ]
}